pyscrcpy/__init__.py
pyscrcpy/const.py
pyscrcpy/control.py
pyscrcpy/core.py
pyscrcpy/scrcpy-server.jar
pyscrcpy-1.0.1.dist-info/LICENSE.txt
pyscrcpy-1.0.1.dist-info/METADATA
pyscrcpy-1.0.1.dist-info/WHEEL
pyscrcpy-1.0.1.dist-info/RECORD
