Metadata-Version: 2.1
Name: pyscrcpy
Version: 1.0.1
Summary: adb and scrcpy, Android screen monitor and control. Compatible with latest python
Home-page: https://github.com/yixinNB/pyscrcpy
License: MIT
Author: yixinNB
Author-email: 58894205+yixinNB@users.noreply.github.com
Requires-Python: >=3.7
Classifier: License :: OSI Approved :: MIT License
Classifier: Programming Language :: Python :: 3
Classifier: Programming Language :: Python :: 3.7
Classifier: Programming Language :: Python :: 3.8
Classifier: Programming Language :: Python :: 3.9
Classifier: Programming Language :: Python :: 3.10
Classifier: Programming Language :: Python :: 3.11
Classifier: Programming Language :: Python :: 3.12
Requires-Dist: adbutils (>=1.0.8,<2.0.0)
Requires-Dist: av (>=9.0.0,<11.0.0)
Requires-Dist: loguru (>=0.7.2,<0.8.0)
Requires-Dist: opencv-python (>=4.5.0)
Project-URL: Repository, https://github.com/yixinNB/pyscrcpy
